pyrsktools/__init__.py
pyrsktools/channels.py
pyrsktools/datatypes.py
pyrsktools/utils.py
pyrsktools/_rsk/__init__.py
pyrsktools/_rsk/_table_map.py
pyrsktools/_rsk/_utils.py
pyrsktools/_rsk/calculators.py
pyrsktools/_rsk/export.py
pyrsktools/_rsk/other.py
pyrsktools/_rsk/post_processors.py
pyrsktools/_rsk/read.py
pyrsktools/_rsk/view.py
pyrsktools/readers/__init__.py
pyrsktools/readers/reader.py
pyrsktools/readers/rskepdesktop.py
pyrsktools/readers/rskfull.py
pyrsktools-1.1.2.dist-info/LICENSE
pyrsktools-1.1.2.dist-info/METADATA
pyrsktools-1.1.2.dist-info/WHEEL
pyrsktools-1.1.2.dist-info/top_level.txt
pyrsktools-1.1.2.dist-info/RECORD
