Metadata-Version: 2.1
Name: pyRSKtools
Version: 1.1.2
Summary: A simple Python toolbox to open RSK SQLite files generated by RBR instruments.
Author: RBR
Author-email: support@rbr-global.com
License: APLv2
Project-URL: Bug Reports, https://rbr-global.com/support/
Project-URL: Wiki, https://docs.rbr-global.com/pyrsktools
Project-URL: Source, https://bitbucket.org/rbr/pyrsktools
Keywords: oceanography rbr rsk ocean
Classifier: Intended Audience :: Science/Research
Classifier: Topic :: Scientific/Engineering
Classifier: License :: OSI Approved :: Apache Software License
Classifier: Programming Language :: Python :: 3
Requires-Python: >=3.8.0
License-File: LICENSE
Requires-Dist: numpy<=1.26.4,>=1.21.0
Requires-Dist: scipy
Requires-Dist: gsw
Requires-Dist: matplotlib
Requires-Dist: cmocean
Provides-Extra: dev
Requires-Dist: build; extra == "dev"
Requires-Dist: twine; extra == "dev"
Requires-Dist: black; extra == "dev"
Requires-Dist: mypy; extra == "dev"
Requires-Dist: sphinx; extra == "dev"
Requires-Dist: sphinx-toolbox; extra == "dev"
Requires-Dist: sphinx-paramlinks; extra == "dev"
